lgraph/__init__.py
lgraph/graph.py
lgraph/utils.py
tests/__init__.py
tests/test_graph.py
ligraph-0.1.0.dist-info/METADATA
ligraph-0.1.0.dist-info/WHEEL
ligraph-0.1.0.dist-info/top_level.txt
ligraph-0.1.0.dist-info/RECORD
